Metadata-Version: 2.1
Name: mandrill-stubs
Version: 0.0.1
Summary: Type declarations for the Mandrill API
Home-page: https://github.com/timmartin/mandrill-stubs
Author: Tim Martin
Author-email: tim@asymptotic.co.uk
License: UNKNOWN
Platform: UNKNOWN
Classifier: Programming Language :: Python :: 3
Classifier: Development Status :: 3 - Alpha
Classifier: License :: OSI Approved :: MIT License
Classifier: Operating System :: OS Independent
Classifier: Typing :: Typed
